{
  "source": "https://stroydocs.com/info/e_veter",
  "api": "http://stroydocs.com/info/getVeterByAjax",
  "stroydocsRows": 652,
  "settlementsTotal": 106,
  "updatedCount": 85,
  "unchangedCount": 0,
  "missing": [
    "Тольятти",
    "Ульяновск",
    "Новокузнецк",
    "Чебоксары",
    "Нижневартовск",
    "Ноябрьск",
    "Норильск",
    "Набережные Челны",
    "Стерлитамак",
    "Курган",
    "Черкесск",
    "Прокопьевск",
    "Дзержинск",
    "Северодвинск",
    "Березники",
    "Копейск",
    "Миасс",
    "Златоуст",
    "Нижнекамск",
    "Альметьевск",
    "Балашова"
  ],
  "ambiguous": [
    {
      "settlement": "Омск",
      "pickedRegion": "Омская область",
      "stroydocsCity": "Омск",
      "regions": [
        "Магаданская область",
        "Омская область"
      ]
    }
  ],
  "updated": [
    {
      "settlement": "Москва",
      "stroydocsCity": "Москва",
      "region": "Московская область",
      "match": "exact",
      "januaryRose": [
        {
          "dir": "С",
          "deg": 0,
          "v": 9
        },
        {
          "dir": "СВ",
          "deg": 45,
          "v": 7
        },
        {
          "dir": "В",
          "deg": 90,
          "v": 7
        },
        {
          "dir": "ЮВ",
          "deg": 135,
          "v": 15
        },
        {
          "dir": "Ю",
          "deg": 180,
          "v": 16
        },
        {
          "dir": "ЮЗ",
          "deg": 225,
          "v": 20
        },
        {
          "dir": "З",
          "deg": 270,
          "v": 13
        },
        {
          "dir": "СЗ",
          "deg": 315,
          "v": 13
        }
      ]
    },
    {
      "settlement": "Санкт-Петербург",
      "stroydocsCity": "Санкт-Петербург",
      "region": "Ленинградская область",
      "match": "exact",
      "januaryRose": [
        {
          "dir": "С",
          "deg": 0,
          "v": 5
        },
        {
          "dir": "СВ",
          "deg": 45,
          "v": 10
        },
        {
          "dir": "В",
          "deg": 90,
          "v": 9
        },
        {
          "dir": "ЮВ",
          "deg": 135,
          "v": 13
        },
        {
          "dir": "Ю",
          "deg": 180,
          "v": 19
        },
        {
          "dir": "ЮЗ",
          "deg": 225,
          "v": 18
        },
        {
          "dir": "З",
          "deg": 270,
          "v": 15
        },
        {
          "dir": "СЗ",
          "deg": 315,
          "v": 11
        }
      ]
    },
    {
      "settlement": "Екатеринбург",
      "stroydocsCity": "Свердловск",
      "region": "Свердловская область",
      "match": "exact",
      "januaryRose": [
        {
          "dir": "С",
          "deg": 0,
          "v": 7
        },
        {
          "dir": "СВ",
          "deg": 45,
          "v": 5
        },
        {
          "dir": "В",
          "deg": 90,
          "v": 4
        },
        {
          "dir": "ЮВ",
          "deg": 135,
          "v": 18
        },
        {
          "dir": "Ю",
          "deg": 180,
          "v": 11
        },
        {
          "dir": "ЮЗ",
          "deg": 225,
          "v": 19
        },
        {
          "dir": "З",
          "deg": 270,
          "v": 30
        },
        {
          "dir": "СЗ",
          "deg": 315,
          "v": 6
        }
      ]
    },
    {
      "settlement": "Новосибирск",
      "stroydocsCity": "Новосибирск",
      "region": "Новосибирская область",
      "match": "exact",
      "januaryRose": [
        {
          "dir": "С",
          "deg": 0,
          "v": 3
        },
        {
          "dir": "СВ",
          "deg": 45,
          "v": 5
        },
        {
          "dir": "В",
          "deg": 90,
          "v": 9
        },
        {
          "dir": "ЮВ",
          "deg": 135,
          "v": 16
        },
        {
          "dir": "Ю",
          "deg": 180,
          "v": 27
        },
        {
          "dir": "ЮЗ",
          "deg": 225,
          "v": 31
        },
        {
          "dir": "З",
          "deg": 270,
          "v": 6
        },
        {
          "dir": "СЗ",
          "deg": 315,
          "v": 3
        }
      ]
    },
    {
      "settlement": "Казань",
      "stroydocsCity": "Казань",
      "region": "Татарская АССР",
      "match": "exact",
      "januaryRose": [
        {
          "dir": "С",
          "deg": 0,
          "v": 11
        },
        {
          "dir": "СВ",
          "deg": 45,
          "v": 4
        },
        {
          "dir": "В",
          "deg": 90,
          "v": 6
        },
        {
          "dir": "ЮВ",
          "deg": 135,
          "v": 20
        },
        {
          "dir": "Ю",
          "deg": 180,
          "v": 28
        },
        {
          "dir": "ЮЗ",
          "deg": 225,
          "v": 12
        },
        {
          "dir": "З",
          "deg": 270,
          "v": 13
        },
        {
          "dir": "СЗ",
          "deg": 315,
          "v": 6
        }
      ]
    },
    {
      "settlement": "Нижний Новгород",
      "stroydocsCity": "Горький",
      "region": "Горьковская область",
      "match": "exact",
      "januaryRose": [
        {
          "dir": "С",
          "deg": 0,
          "v": 6
        },
        {
          "dir": "СВ",
          "deg": 45,
          "v": 6
        },
        {
          "dir": "В",
          "deg": 90,
          "v": 8
        },
        {
          "dir": "ЮВ",
          "deg": 135,
          "v": 12
        },
        {
          "dir": "Ю",
          "deg": 180,
          "v": 18
        },
        {
          "dir": "ЮЗ",
          "deg": 225,
          "v": 27
        },
        {
          "dir": "З",
          "deg": 270,
          "v": 14
        },
        {
          "dir": "СЗ",
          "deg": 315,
          "v": 9
        }
      ]
    },
    {
      "settlement": "Челябинск",
      "stroydocsCity": "Челябинск",
      "region": "Челябинская область",
      "match": "exact",
      "januaryRose": [
        {
          "dir": "С",
          "deg": 0,
          "v": 7
        },
        {
          "dir": "СВ",
          "deg": 45,
          "v": 3
        },
        {
          "dir": "В",
          "deg": 90,
          "v": 2
        },
        {
          "dir": "ЮВ",
          "deg": 135,
          "v": 7
        },
        {
          "dir": "Ю",
          "deg": 180,
          "v": 20
        },
        {
          "dir": "ЮЗ",
          "deg": 225,
          "v": 38
        },
        {
          "dir": "З",
          "deg": 270,
          "v": 10
        },
        {
          "dir": "СЗ",
          "deg": 315,
          "v": 13
        }
      ]
    },
    {
      "settlement": "Самара",
      "stroydocsCity": "Куйбышев",
      "region": "Куйбышевская область",
      "match": "exact",
      "januaryRose": [
        {
          "dir": "С",
          "deg": 0,
          "v": 10
        },
        {
          "dir": "СВ",
          "deg": 45,
          "v": 6
        },
        {
          "dir": "В",
          "deg": 90,
          "v": 20
        },
        {
          "dir": "ЮВ",
          "deg": 135,
          "v": 11
        },
        {
          "dir": "Ю",
          "deg": 180,
          "v": 12
        },
        {
          "dir": "ЮЗ",
          "deg": 225,
          "v": 16
        },
        {
          "dir": "З",
          "deg": 270,
          "v": 13
        },
        {
          "dir": "СЗ",
          "deg": 315,
          "v": 7
        }
      ]
    },
    {
      "settlement": "Омск",
      "stroydocsCity": "Омск",
      "region": "Омская область",
      "match": "exact",
      "januaryRose": [
        {
          "dir": "С",
          "deg": 0,
          "v": 4
        },
        {
          "dir": "СВ",
          "deg": 45,
          "v": 6
        },
        {
          "dir": "В",
          "deg": 90,
          "v": 14
        },
        {
          "dir": "ЮВ",
          "deg": 135,
          "v": 10
        },
        {
          "dir": "Ю",
          "deg": 180,
          "v": 20
        },
        {
          "dir": "ЮЗ",
          "deg": 225,
          "v": 27
        },
        {
          "dir": "З",
          "deg": 270,
          "v": 12
        },
        {
          "dir": "СЗ",
          "deg": 315,
          "v": 7
        }
      ]
    },
    {
      "settlement": "Ростов-на-Дону",
      "stroydocsCity": "Ростов-на-Дону",
      "region": "Ростовская область",
      "match": "exact",
      "januaryRose": [
        {
          "dir": "С",
          "deg": 0,
          "v": 4
        },
        {
          "dir": "СВ",
          "deg": 45,
          "v": 14
        },
        {
          "dir": "В",
          "deg": 90,
          "v": 33
        },
        {
          "dir": "ЮВ",
          "deg": 135,
          "v": 10
        },
        {
          "dir": "Ю",
          "deg": 180,
          "v": 4
        },
        {
          "dir": "ЮЗ",
          "deg": 225,
          "v": 12
        },
        {
          "dir": "З",
          "deg": 270,
          "v": 17
        },
        {
          "dir": "СЗ",
          "deg": 315,
          "v": 6
        }
      ]
    },
    {
      "settlement": "Уфа",
      "stroydocsCity": "Уфа",
      "region": "Башкирская АССР",
      "match": "exact",
      "januaryRose": [
        {
          "dir": "С",
          "deg": 0,
          "v": 9
        },
        {
          "dir": "СВ",
          "deg": 45,
          "v": 4
        },
        {
          "dir": "В",
          "deg": 90,
          "v": 2
        },
        {
          "dir": "ЮВ",
          "deg": 135,
          "v": 8
        },
        {
          "dir": "Ю",
          "deg": 180,
          "v": 42
        },
        {
          "dir": "ЮЗ",
          "deg": 225,
          "v": 20
        },
        {
          "dir": "З",
          "deg": 270,
          "v": 6
        },
        {
          "dir": "СЗ",
          "deg": 315,
          "v": 9
        }
      ]
    },
    {
      "settlement": "Красноярск",
      "stroydocsCity": "Красноярск",
      "region": "Красноярский край",
      "match": "exact",
      "januaryRose": [
        {
          "dir": "С",
          "deg": 0,
          "v": 1
        },
        {
          "dir": "СВ",
          "deg": 45,
          "v": 1
        },
        {
          "dir": "В",
          "deg": 90,
          "v": 2
        },
        {
          "dir": "ЮВ",
          "deg": 135,
          "v": 1
        },
        {
          "dir": "Ю",
          "deg": 180,
          "v": 15
        },
        {
          "dir": "ЮЗ",
          "deg": 225,
          "v": 64
        },
        {
          "dir": "З",
          "deg": 270,
          "v": 15
        },
        {
          "dir": "СЗ",
          "deg": 315,
          "v": 1
        }
      ]
    },
    {
      "settlement": "Воронеж",
      "stroydocsCity": "Воронеж",
      "region": "Воронежская область",
      "match": "exact",
      "januaryRose": [
        {
          "dir": "С",
          "deg": 0,
          "v": 10
        },
        {
          "dir": "СВ",
          "deg": 45,
          "v": 11
        },
        {
          "dir": "В",
          "deg": 90,
          "v": 12
        },
        {
          "dir": "ЮВ",
          "deg": 135,
          "v": 15
        },
        {
          "dir": "Ю",
          "deg": 180,
          "v": 12
        },
        {
          "dir": "ЮЗ",
          "deg": 225,
          "v": 14
        },
        {
          "dir": "З",
          "deg": 270,
          "v": 16
        },
        {
          "dir": "СЗ",
          "deg": 315,
          "v": 10
        }
      ]
    },
    {
      "settlement": "Пермь",
      "stroydocsCity": "Пермь",
      "region": "Пермская область",
      "match": "exact",
      "januaryRose": [
        {
          "dir": "С",
          "deg": 0,
          "v": 6
        },
        {
          "dir": "СВ",
          "deg": 45,
          "v": 6
        },
        {
          "dir": "В",
          "deg": 90,
          "v": 10
        },
        {
          "dir": "ЮВ",
          "deg": 135,
          "v": 18
        },
        {
          "dir": "Ю",
          "deg": 180,
          "v": 21
        },
        {
          "dir": "ЮЗ",
          "deg": 225,
          "v": 22
        },
        {
          "dir": "З",
          "deg": 270,
          "v": 11
        },
        {
          "dir": "СЗ",
          "deg": 315,
          "v": 6
        }
      ]
    },
    {
      "settlement": "Волгоград",
      "stroydocsCity": "Волгоград",
      "region": "Волгоградская область",
      "match": "exact",
      "januaryRose": [
        {
          "dir": "С",
          "deg": 0,
          "v": 6
        },
        {
          "dir": "СВ",
          "deg": 45,
          "v": 18
        },
        {
          "dir": "В",
          "deg": 90,
          "v": 18
        },
        {
          "dir": "ЮВ",
          "deg": 135,
          "v": 14
        },
        {
          "dir": "Ю",
          "deg": 180,
          "v": 8
        },
        {
          "dir": "ЮЗ",
          "deg": 225,
          "v": 10
        },
        {
          "dir": "З",
          "deg": 270,
          "v": 15
        },
        {
          "dir": "СЗ",
          "deg": 315,
          "v": 11
        }
      ]
    },
    {
      "settlement": "Краснодар",
      "stroydocsCity": "Краснодар",
      "region": "Краснодарский край",
      "match": "exact",
      "januaryRose": [
        {
          "dir": "С",
          "deg": 0,
          "v": 5
        },
        {
          "dir": "СВ",
          "deg": 45,
          "v": 21
        },
        {
          "dir": "В",
          "deg": 90,
          "v": 24
        },
        {
          "dir": "ЮВ",
          "deg": 135,
          "v": 6
        },
        {
          "dir": "Ю",
          "deg": 180,
          "v": 7
        },
        {
          "dir": "ЮЗ",
          "deg": 225,
          "v": 14
        },
        {
          "dir": "З",
          "deg": 270,
          "v": 14
        },
        {
          "dir": "СЗ",
          "deg": 315,
          "v": 9
        }
      ]
    },
    {
      "settlement": "Саратов",
      "stroydocsCity": "Саратов",
      "region": "Саратовская область",
      "match": "exact",
      "januaryRose": [
        {
          "dir": "С",
          "deg": 0,
          "v": 6
        },
        {
          "dir": "СВ",
          "deg": 45,
          "v": 2
        },
        {
          "dir": "В",
          "deg": 90,
          "v": 10
        },
        {
          "dir": "ЮВ",
          "deg": 135,
          "v": 17
        },
        {
          "dir": "Ю",
          "deg": 180,
          "v": 21
        },
        {
          "dir": "ЮЗ",
          "deg": 225,
          "v": 7
        },
        {
          "dir": "З",
          "deg": 270,
          "v": 15
        },
        {
          "dir": "СЗ",
          "deg": 315,
          "v": 21
        }
      ]
    },
    {
      "settlement": "Тюмень",
      "stroydocsCity": "Гюмень",
      "region": "Тюменская область",
      "match": "exact",
      "januaryRose": [
        {
          "dir": "С",
          "deg": 0,
          "v": 3
        },
        {
          "dir": "СВ",
          "deg": 45,
          "v": 3
        },
        {
          "dir": "В",
          "deg": 90,
          "v": 4
        },
        {
          "dir": "ЮВ",
          "deg": 135,
          "v": 11
        },
        {
          "dir": "Ю",
          "deg": 180,
          "v": 22
        },
        {
          "dir": "ЮЗ",
          "deg": 225,
          "v": 33
        },
        {
          "dir": "З",
          "deg": 270,
          "v": 16
        },
        {
          "dir": "СЗ",
          "deg": 315,
          "v": 1
        }
      ]
    },
    {
      "settlement": "Ижевск",
      "stroydocsCity": "Ижевск",
      "region": "Удмуртская АССР",
      "match": "exact",
      "januaryRose": [
        {
          "dir": "С",
          "deg": 0,
          "v": 6
        },
        {
          "dir": "СВ",
          "deg": 45,
          "v": 12
        },
        {
          "dir": "В",
          "deg": 90,
          "v": 7
        },
        {
          "dir": "ЮВ",
          "deg": 135,
          "v": 11
        },
        {
          "dir": "Ю",
          "deg": 180,
          "v": 17
        },
        {
          "dir": "ЮЗ",
          "deg": 225,
          "v": 33
        },
        {
          "dir": "З",
          "deg": 270,
          "v": 6
        },
        {
          "dir": "СЗ",
          "deg": 315,
          "v": 8
        }
      ]
    },
    {
      "settlement": "Барнаул",
      "stroydocsCity": "Барнаул",
      "region": "Алтайский край",
      "match": "exact",
      "januaryRose": [
        {
          "dir": "С",
          "deg": 0,
          "v": 4
        },
        {
          "dir": "СВ",
          "deg": 45,
          "v": 14
        },
        {
          "dir": "В",
          "deg": 90,
          "v": 3
        },
        {
          "dir": "ЮВ",
          "deg": 135,
          "v": 8
        },
        {
          "dir": "Ю",
          "deg": 180,
          "v": 17
        },
        {
          "dir": "ЮЗ",
          "deg": 225,
          "v": 37
        },
        {
          "dir": "З",
          "deg": 270,
          "v": 14
        },
        {
          "dir": "СЗ",
          "deg": 315,
          "v": 3
        }
      ]
    },
    {
      "settlement": "Иркутск",
      "stroydocsCity": "Иркутск",
      "region": "Иркутская область",
      "match": "exact",
      "januaryRose": [
        {
          "dir": "С",
          "deg": 0,
          "v": 6
        },
        {
          "dir": "СВ",
          "deg": 45,
          "v": 9
        },
        {
          "dir": "В",
          "deg": 90,
          "v": 14
        },
        {
          "dir": "ЮВ",
          "deg": 135,
          "v": 34
        },
        {
          "dir": "Ю",
          "deg": 180,
          "v": 3
        },
        {
          "dir": "ЮЗ",
          "deg": 225,
          "v": 1
        },
        {
          "dir": "З",
          "deg": 270,
          "v": 7
        },
        {
          "dir": "СЗ",
          "deg": 315,
          "v": 26
        }
      ]
    },
    {
      "settlement": "Хабаровск",
      "stroydocsCity": "Хабаровск",
      "region": "Хаборавский край",
      "match": "exact",
      "januaryRose": [
        {
          "dir": "С",
          "deg": 0,
          "v": 2
        },
        {
          "dir": "СВ",
          "deg": 45,
          "v": 7
        },
        {
          "dir": "В",
          "deg": 90,
          "v": 6
        },
        {
          "dir": "ЮВ",
          "deg": 135,
          "v": 2
        },
        {
          "dir": "Ю",
          "deg": 180,
          "v": 2
        },
        {
          "dir": "ЮЗ",
          "deg": 225,
          "v": 74
        },
        {
          "dir": "З",
          "deg": 270,
          "v": 6
        },
        {
          "dir": "СЗ",
          "deg": 315,
          "v": 1
        }
      ]
    },
    {
      "settlement": "Ярославль",
      "stroydocsCity": "Ярославль",
      "region": "Ярославская область",
      "match": "exact",
      "januaryRose": [
        {
          "dir": "С",
          "deg": 0,
          "v": 7
        },
        {
          "dir": "СВ",
          "deg": 45,
          "v": 6
        },
        {
          "dir": "В",
          "deg": 90,
          "v": 8
        },
        {
          "dir": "ЮВ",
          "deg": 135,
          "v": 12
        },
        {
          "dir": "Ю",
          "deg": 180,
          "v": 20
        },
        {
          "dir": "ЮЗ",
          "deg": 225,
          "v": 21
        },
        {
          "dir": "З",
          "deg": 270,
          "v": 14
        },
        {
          "dir": "СЗ",
          "deg": 315,
          "v": 12
        }
      ]
    },
    {
      "settlement": "Владивосток",
      "stroydocsCity": "Владивосток",
      "region": "Приморский край",
      "match": "exact",
      "januaryRose": [
        {
          "dir": "С",
          "deg": 0,
          "v": 7
        },
        {
          "dir": "СВ",
          "deg": 45,
          "v": 3
        },
        {
          "dir": "В",
          "deg": 90,
          "v": 1
        },
        {
          "dir": "ЮВ",
          "deg": 135,
          "v": 9
        },
        {
          "dir": "Ю",
          "deg": 180,
          "v": 1
        },
        {
          "dir": "ЮЗ",
          "deg": 225,
          "v": 2
        },
        {
          "dir": "З",
          "deg": 270,
          "v": 2
        },
        {
          "dir": "СЗ",
          "deg": 315,
          "v": 8
        }
      ]
    },
    {
      "settlement": "Махачкала",
      "stroydocsCity": "Махачкала",
      "region": "Дагестанская АССР",
      "match": "exact",
      "januaryRose": [
        {
          "dir": "С",
          "deg": 0,
          "v": 2
        },
        {
          "dir": "СВ",
          "deg": 45,
          "v": 1
        },
        {
          "dir": "В",
          "deg": 90,
          "v": 2
        },
        {
          "dir": "ЮВ",
          "deg": 135,
          "v": 31
        },
        {
          "dir": "Ю",
          "deg": 180,
          "v": 3
        },
        {
          "dir": "ЮЗ",
          "deg": 225,
          "v": 10
        },
        {
          "dir": "З",
          "deg": 270,
          "v": 17
        },
        {
          "dir": "СЗ",
          "deg": 315,
          "v": 44
        }
      ]
    },
    {
      "settlement": "Томск",
      "stroydocsCity": "Томск",
      "region": "Томская область",
      "match": "exact",
      "januaryRose": [
        {
          "dir": "С",
          "deg": 0,
          "v": 6
        },
        {
          "dir": "СВ",
          "deg": 45,
          "v": 10
        },
        {
          "dir": "В",
          "deg": 90,
          "v": 8
        },
        {
          "dir": "ЮВ",
          "deg": 135,
          "v": 5
        },
        {
          "dir": "Ю",
          "deg": 180,
          "v": 49
        },
        {
          "dir": "ЮЗ",
          "deg": 225,
          "v": 17
        },
        {
          "dir": "З",
          "deg": 270,
          "v": 2
        },
        {
          "dir": "СЗ",
          "deg": 315,
          "v": 3
        }
      ]
    },
    {
      "settlement": "Оренбург",
      "stroydocsCity": "Оренбург",
      "region": "Оренбургская область",
      "match": "exact",
      "januaryRose": [
        {
          "dir": "С",
          "deg": 0,
          "v": 10
        },
        {
          "dir": "СВ",
          "deg": 45,
          "v": 11
        },
        {
          "dir": "В",
          "deg": 90,
          "v": 29
        },
        {
          "dir": "ЮВ",
          "deg": 135,
          "v": 13
        },
        {
          "dir": "Ю",
          "deg": 180,
          "v": 7
        },
        {
          "dir": "ЮЗ",
          "deg": 225,
          "v": 17
        },
        {
          "dir": "З",
          "deg": 270,
          "v": 10
        },
        {
          "dir": "СЗ",
          "deg": 315,
          "v": 3
        }
      ]
    },
    {
      "settlement": "Кемерово",
      "stroydocsCity": "Кемерово",
      "region": "Кемеровская область",
      "match": "exact",
      "januaryRose": [
        {
          "dir": "С",
          "deg": 0,
          "v": 1
        },
        {
          "dir": "СВ",
          "deg": 45,
          "v": 0
        },
        {
          "dir": "В",
          "deg": 90,
          "v": 3
        },
        {
          "dir": "ЮВ",
          "deg": 135,
          "v": 29
        },
        {
          "dir": "Ю",
          "deg": 180,
          "v": 21
        },
        {
          "dir": "ЮЗ",
          "deg": 225,
          "v": 34
        },
        {
          "dir": "З",
          "deg": 270,
          "v": 6
        },
        {
          "dir": "СЗ",
          "deg": 315,
          "v": 6
        }
      ]
    },
    {
      "settlement": "Рязань",
      "stroydocsCity": "Рязань",
      "region": "Рязанская область",
      "match": "exact",
      "januaryRose": [
        {
          "dir": "С",
          "deg": 0,
          "v": 7
        },
        {
          "dir": "СВ",
          "deg": 45,
          "v": 5
        },
        {
          "dir": "В",
          "deg": 90,
          "v": 8
        },
        {
          "dir": "ЮВ",
          "deg": 135,
          "v": 15
        },
        {
          "dir": "Ю",
          "deg": 180,
          "v": 17
        },
        {
          "dir": "ЮЗ",
          "deg": 225,
          "v": 23
        },
        {
          "dir": "З",
          "deg": 270,
          "v": 14
        },
        {
          "dir": "СЗ",
          "deg": 315,
          "v": 11
        }
      ]
    },
    {
      "settlement": "Астрахань",
      "stroydocsCity": "Астрахань",
      "region": "Астраханская область",
      "match": "exact",
      "januaryRose": [
        {
          "dir": "С",
          "deg": 0,
          "v": 9
        },
        {
          "dir": "СВ",
          "deg": 45,
          "v": 15
        },
        {
          "dir": "В",
          "deg": 90,
          "v": 22
        },
        {
          "dir": "ЮВ",
          "deg": 135,
          "v": 14
        },
        {
          "dir": "Ю",
          "deg": 180,
          "v": 5
        },
        {
          "dir": "ЮЗ",
          "deg": 225,
          "v": 10
        },
        {
          "dir": "З",
          "deg": 270,
          "v": 15
        },
        {
          "dir": "СЗ",
          "deg": 315,
          "v": 10
        }
      ]
    },
    {
      "settlement": "Пенза",
      "stroydocsCity": "Пенза",
      "region": "Пензенская область",
      "match": "exact",
      "januaryRose": [
        {
          "dir": "С",
          "deg": 0,
          "v": 9
        },
        {
          "dir": "СВ",
          "deg": 45,
          "v": 3
        },
        {
          "dir": "В",
          "deg": 90,
          "v": 3
        },
        {
          "dir": "ЮВ",
          "deg": 135,
          "v": 20
        },
        {
          "dir": "Ю",
          "deg": 180,
          "v": 29
        },
        {
          "dir": "ЮЗ",
          "deg": 225,
          "v": 14
        },
        {
          "dir": "З",
          "deg": 270,
          "v": 6
        },
        {
          "dir": "СЗ",
          "deg": 315,
          "v": 16
        }
      ]
    },
    {
      "settlement": "Липецк",
      "stroydocsCity": "Липецк",
      "region": "Липецкая область",
      "match": "exact",
      "januaryRose": [
        {
          "dir": "С",
          "deg": 0,
          "v": 12
        },
        {
          "dir": "СВ",
          "deg": 45,
          "v": 8
        },
        {
          "dir": "В",
          "deg": 90,
          "v": 8
        },
        {
          "dir": "ЮВ",
          "deg": 135,
          "v": 15
        },
        {
          "dir": "Ю",
          "deg": 180,
          "v": 13
        },
        {
          "dir": "ЮЗ",
          "deg": 225,
          "v": 17
        },
        {
          "dir": "З",
          "deg": 270,
          "v": 12
        },
        {
          "dir": "СЗ",
          "deg": 315,
          "v": 15
        }
      ]
    },
    {
      "settlement": "Тула",
      "stroydocsCity": "Тула",
      "region": "Тульская область",
      "match": "exact",
      "januaryRose": [
        {
          "dir": "С",
          "deg": 0,
          "v": 7
        },
        {
          "dir": "СВ",
          "deg": 45,
          "v": 5
        },
        {
          "dir": "В",
          "deg": 90,
          "v": 13
        },
        {
          "dir": "ЮВ",
          "deg": 135,
          "v": 14
        },
        {
          "dir": "Ю",
          "deg": 180,
          "v": 13
        },
        {
          "dir": "ЮЗ",
          "deg": 225,
          "v": 19
        },
        {
          "dir": "З",
          "deg": 270,
          "v": 18
        },
        {
          "dir": "СЗ",
          "deg": 315,
          "v": 11
        }
      ]
    },
    {
      "settlement": "Киров",
      "stroydocsCity": "Киров",
      "region": "Кировская область",
      "match": "exact",
      "januaryRose": [
        {
          "dir": "С",
          "deg": 0,
          "v": 7
        },
        {
          "dir": "СВ",
          "deg": 45,
          "v": 6
        },
        {
          "dir": "В",
          "deg": 90,
          "v": 11
        },
        {
          "dir": "ЮВ",
          "deg": 135,
          "v": 19
        },
        {
          "dir": "Ю",
          "deg": 180,
          "v": 17
        },
        {
          "dir": "ЮЗ",
          "deg": 225,
          "v": 15
        },
        {
          "dir": "З",
          "deg": 270,
          "v": 16
        },
        {
          "dir": "СЗ",
          "deg": 315,
          "v": 9
        }
      ]
    },
    {
      "settlement": "Калининград",
      "stroydocsCity": "Калининград",
      "region": "Калининградская область",
      "match": "exact",
      "januaryRose": [
        {
          "dir": "С",
          "deg": 0,
          "v": 4
        },
        {
          "dir": "СВ",
          "deg": 45,
          "v": 9
        },
        {
          "dir": "В",
          "deg": 90,
          "v": 8
        },
        {
          "dir": "ЮВ",
          "deg": 135,
          "v": 15
        },
        {
          "dir": "Ю",
          "deg": 180,
          "v": 17
        },
        {
          "dir": "ЮЗ",
          "deg": 225,
          "v": 28
        },
        {
          "dir": "З",
          "deg": 270,
          "v": 13
        },
        {
          "dir": "СЗ",
          "deg": 315,
          "v": 6
        }
      ]
    },
    {
      "settlement": "Брянск",
      "stroydocsCity": "Брянск",
      "region": "Брянская область",
      "match": "exact",
      "januaryRose": [
        {
          "dir": "С",
          "deg": 0,
          "v": 6
        },
        {
          "dir": "СВ",
          "deg": 45,
          "v": 10
        },
        {
          "dir": "В",
          "deg": 90,
          "v": 13
        },
        {
          "dir": "ЮВ",
          "deg": 135,
          "v": 16
        },
        {
          "dir": "Ю",
          "deg": 180,
          "v": 11
        },
        {
          "dir": "ЮЗ",
          "deg": 225,
          "v": 18
        },
        {
          "dir": "З",
          "deg": 270,
          "v": 15
        },
        {
          "dir": "СЗ",
          "deg": 315,
          "v": 11
        }
      ]
    },
    {
      "settlement": "Курск",
      "stroydocsCity": "Курск",
      "region": "Курская область",
      "match": "exact",
      "januaryRose": [
        {
          "dir": "С",
          "deg": 0,
          "v": 7
        },
        {
          "dir": "СВ",
          "deg": 45,
          "v": 14
        },
        {
          "dir": "В",
          "deg": 90,
          "v": 13
        },
        {
          "dir": "ЮВ",
          "deg": 135,
          "v": 15
        },
        {
          "dir": "Ю",
          "deg": 180,
          "v": 8
        },
        {
          "dir": "ЮЗ",
          "deg": 225,
          "v": 17
        },
        {
          "dir": "З",
          "deg": 270,
          "v": 16
        },
        {
          "dir": "СЗ",
          "deg": 315,
          "v": 10
        }
      ]
    },
    {
      "settlement": "Магнитогорск",
      "stroydocsCity": "Магнитогорск",
      "region": "Челябинская область",
      "match": "exact",
      "januaryRose": [
        {
          "dir": "С",
          "deg": 0,
          "v": 20
        },
        {
          "dir": "СВ",
          "deg": 45,
          "v": 11
        },
        {
          "dir": "В",
          "deg": 90,
          "v": 1
        },
        {
          "dir": "ЮВ",
          "deg": 135,
          "v": 2
        },
        {
          "dir": "Ю",
          "deg": 180,
          "v": 26
        },
        {
          "dir": "ЮЗ",
          "deg": 225,
          "v": 23
        },
        {
          "dir": "З",
          "deg": 270,
          "v": 11
        },
        {
          "dir": "СЗ",
          "deg": 315,
          "v": 6
        }
      ]
    },
    {
      "settlement": "Тверь",
      "stroydocsCity": "Калинин",
      "region": "Калининская область",
      "match": "exact",
      "januaryRose": [
        {
          "dir": "С",
          "deg": 0,
          "v": 10
        },
        {
          "dir": "СВ",
          "deg": 45,
          "v": 11
        },
        {
          "dir": "В",
          "deg": 90,
          "v": 6
        },
        {
          "dir": "ЮВ",
          "deg": 135,
          "v": 10
        },
        {
          "dir": "Ю",
          "deg": 180,
          "v": 13
        },
        {
          "dir": "ЮЗ",
          "deg": 225,
          "v": 28
        },
        {
          "dir": "З",
          "deg": 270,
          "v": 15
        },
        {
          "dir": "СЗ",
          "deg": 315,
          "v": 7
        }
      ]
    },
    {
      "settlement": "Ставрополь",
      "stroydocsCity": "Ставрополь",
      "region": "Ставропольский край",
      "match": "exact",
      "januaryRose": [
        {
          "dir": "С",
          "deg": 0,
          "v": 1
        },
        {
          "dir": "СВ",
          "deg": 45,
          "v": 4
        },
        {
          "dir": "В",
          "deg": 90,
          "v": 14
        },
        {
          "dir": "ЮВ",
          "deg": 135,
          "v": 20
        },
        {
          "dir": "Ю",
          "deg": 180,
          "v": 8
        },
        {
          "dir": "ЮЗ",
          "deg": 225,
          "v": 19
        },
        {
          "dir": "З",
          "deg": 270,
          "v": 27
        },
        {
          "dir": "СЗ",
          "deg": 315,
          "v": 7
        }
      ]
    },
    {
      "settlement": "Иваново",
      "stroydocsCity": "Иваново",
      "region": "Ивановская область",
      "match": "exact",
      "januaryRose": [
        {
          "dir": "С",
          "deg": 0,
          "v": 8
        },
        {
          "dir": "СВ",
          "deg": 45,
          "v": 3
        },
        {
          "dir": "В",
          "deg": 90,
          "v": 9
        },
        {
          "dir": "ЮВ",
          "deg": 135,
          "v": 13
        },
        {
          "dir": "Ю",
          "deg": 180,
          "v": 20
        },
        {
          "dir": "ЮЗ",
          "deg": 225,
          "v": 21
        },
        {
          "dir": "З",
          "deg": 270,
          "v": 12
        },
        {
          "dir": "СЗ",
          "deg": 315,
          "v": 10
        }
      ]
    },
    {
      "settlement": "Белгород",
      "stroydocsCity": "Белгород",
      "region": "Белгородская область",
      "match": "exact",
      "januaryRose": [
        {
          "dir": "С",
          "deg": 0,
          "v": 8
        },
        {
          "dir": "СВ",
          "deg": 45,
          "v": 14
        },
        {
          "dir": "В",
          "deg": 90,
          "v": 9
        },
        {
          "dir": "ЮВ",
          "deg": 135,
          "v": 14
        },
        {
          "dir": "Ю",
          "deg": 180,
          "v": 11
        },
        {
          "dir": "ЮЗ",
          "deg": 225,
          "v": 17
        },
        {
          "dir": "З",
          "deg": 270,
          "v": 18
        },
        {
          "dir": "СЗ",
          "deg": 315,
          "v": 9
        }
      ]
    },
    {
      "settlement": "Сочи",
      "stroydocsCity": "Сочи",
      "region": "Краснодарский край",
      "match": "exact",
      "januaryRose": [
        {
          "dir": "С",
          "deg": 0,
          "v": 12
        },
        {
          "dir": "СВ",
          "deg": 45,
          "v": 29
        },
        {
          "dir": "В",
          "deg": 90,
          "v": 21
        },
        {
          "dir": "ЮВ",
          "deg": 135,
          "v": 21
        },
        {
          "dir": "Ю",
          "deg": 180,
          "v": 4
        },
        {
          "dir": "ЮЗ",
          "deg": 225,
          "v": 2
        },
        {
          "dir": "З",
          "deg": 270,
          "v": 4
        },
        {
          "dir": "СЗ",
          "deg": 315,
          "v": 7
        }
      ]
    },
    {
      "settlement": "Мурманск",
      "stroydocsCity": "Мурманск",
      "region": "Мурманская область",
      "match": "exact",
      "januaryRose": [
        {
          "dir": "С",
          "deg": 0,
          "v": 3
        },
        {
          "dir": "СВ",
          "deg": 45,
          "v": 3
        },
        {
          "dir": "В",
          "deg": 90,
          "v": 1
        },
        {
          "dir": "ЮВ",
          "deg": 135,
          "v": 4
        },
        {
          "dir": "Ю",
          "deg": 180,
          "v": 58
        },
        {
          "dir": "ЮЗ",
          "deg": 225,
          "v": 21
        },
        {
          "dir": "З",
          "deg": 270,
          "v": 5
        },
        {
          "dir": "СЗ",
          "deg": 315,
          "v": 5
        }
      ]
    },
    {
      "settlement": "Владикавказ",
      "stroydocsCity": "Орджоникидзе",
      "region": "Северо-Осетинская АССР",
      "match": "exact",
      "januaryRose": [
        {
          "dir": "С",
          "deg": 0,
          "v": 6
        },
        {
          "dir": "СВ",
          "deg": 45,
          "v": 6
        },
        {
          "dir": "В",
          "deg": 90,
          "v": 4
        },
        {
          "dir": "ЮВ",
          "deg": 135,
          "v": 23
        },
        {
          "dir": "Ю",
          "deg": 180,
          "v": 20
        },
        {
          "dir": "ЮЗ",
          "deg": 225,
          "v": 9
        },
        {
          "dir": "З",
          "deg": 270,
          "v": 19
        },
        {
          "dir": "СЗ",
          "deg": 315,
          "v": 13
        }
      ]
    },
    {
      "settlement": "Грозный",
      "stroydocsCity": "Грозный",
      "region": "Чечено-Ингушская АССР",
      "match": "exact",
      "januaryRose": [
        {
          "dir": "С",
          "deg": 0,
          "v": 4
        },
        {
          "dir": "СВ",
          "deg": 45,
          "v": 9
        },
        {
          "dir": "В",
          "deg": 90,
          "v": 12
        },
        {
          "dir": "ЮВ",
          "deg": 135,
          "v": 15
        },
        {
          "dir": "Ю",
          "deg": 180,
          "v": 4
        },
        {
          "dir": "ЮЗ",
          "deg": 225,
          "v": 8
        },
        {
          "dir": "З",
          "deg": 270,
          "v": 16
        },
        {
          "dir": "СЗ",
          "deg": 315,
          "v": 32
        }
      ]
    },
    {
      "settlement": "Смоленск",
      "stroydocsCity": "Смоленск",
      "region": "Смоленская область",
      "match": "exact",
      "januaryRose": [
        {
          "dir": "С",
          "deg": 0,
          "v": 7
        },
        {
          "dir": "СВ",
          "deg": 45,
          "v": 9
        },
        {
          "dir": "В",
          "deg": 90,
          "v": 13
        },
        {
          "dir": "ЮВ",
          "deg": 135,
          "v": 12
        },
        {
          "dir": "Ю",
          "deg": 180,
          "v": 16
        },
        {
          "dir": "ЮЗ",
          "deg": 225,
          "v": 17
        },
        {
          "dir": "З",
          "deg": 270,
          "v": 14
        },
        {
          "dir": "СЗ",
          "deg": 315,
          "v": 12
        }
      ]
    },
    {
      "settlement": "Владимир",
      "stroydocsCity": "Владимир",
      "region": "Владимирская область",
      "match": "exact",
      "januaryRose": [
        {
          "dir": "С",
          "deg": 0,
          "v": 13
        },
        {
          "dir": "СВ",
          "deg": 45,
          "v": 8
        },
        {
          "dir": "В",
          "deg": 90,
          "v": 4
        },
        {
          "dir": "ЮВ",
          "deg": 135,
          "v": 12
        },
        {
          "dir": "Ю",
          "deg": 180,
          "v": 21
        },
        {
          "dir": "ЮЗ",
          "deg": 225,
          "v": 23
        },
        {
          "dir": "З",
          "deg": 270,
          "v": 7
        },
        {
          "dir": "СЗ",
          "deg": 315,
          "v": 12
        }
      ]
    },
    {
      "settlement": "Калуга",
      "stroydocsCity": "Калуга",
      "region": "Калужская область",
      "match": "exact",
      "januaryRose": [
        {
          "dir": "С",
          "deg": 0,
          "v": 7
        },
        {
          "dir": "СВ",
          "deg": 45,
          "v": 9
        },
        {
          "dir": "В",
          "deg": 90,
          "v": 14
        },
        {
          "dir": "ЮВ",
          "deg": 135,
          "v": 12
        },
        {
          "dir": "Ю",
          "deg": 180,
          "v": 13
        },
        {
          "dir": "ЮЗ",
          "deg": 225,
          "v": 23
        },
        {
          "dir": "З",
          "deg": 270,
          "v": 14
        },
        {
          "dir": "СЗ",
          "deg": 315,
          "v": 8
        }
      ]
    },
    {
      "settlement": "Орёл",
      "stroydocsCity": "Орел",
      "region": "Орловская область",
      "match": "exact",
      "januaryRose": [
        {
          "dir": "С",
          "deg": 0,
          "v": 8
        },
        {
          "dir": "СВ",
          "deg": 45,
          "v": 10
        },
        {
          "dir": "В",
          "deg": 90,
          "v": 7
        },
        {
          "dir": "ЮВ",
          "deg": 135,
          "v": 13
        },
        {
          "dir": "Ю",
          "deg": 180,
          "v": 19
        },
        {
          "dir": "ЮЗ",
          "deg": 225,
          "v": 20
        },
        {
          "dir": "З",
          "deg": 270,
          "v": 12
        },
        {
          "dir": "СЗ",
          "deg": 315,
          "v": 11
        }
      ]
    },
    {
      "settlement": "Тамбов",
      "stroydocsCity": "Тамбов",
      "region": "Тамбовская область",
      "match": "exact",
      "januaryRose": [
        {
          "dir": "С",
          "deg": 0,
          "v": 10
        },
        {
          "dir": "СВ",
          "deg": 45,
          "v": 5
        },
        {
          "dir": "В",
          "deg": 90,
          "v": 8
        },
        {
          "dir": "ЮВ",
          "deg": 135,
          "v": 21
        },
        {
          "dir": "Ю",
          "deg": 180,
          "v": 20
        },
        {
          "dir": "ЮЗ",
          "deg": 225,
          "v": 15
        },
        {
          "dir": "З",
          "deg": 270,
          "v": 10
        },
        {
          "dir": "СЗ",
          "deg": 315,
          "v": 11
        }
      ]
    },
    {
      "settlement": "Кострома",
      "stroydocsCity": "Кострома",
      "region": "Костромская область",
      "match": "exact",
      "januaryRose": [
        {
          "dir": "С",
          "deg": 0,
          "v": 10
        },
        {
          "dir": "СВ",
          "deg": 45,
          "v": 5
        },
        {
          "dir": "В",
          "deg": 90,
          "v": 6
        },
        {
          "dir": "ЮВ",
          "deg": 135,
          "v": 19
        },
        {
          "dir": "Ю",
          "deg": 180,
          "v": 20
        },
        {
          "dir": "ЮЗ",
          "deg": 225,
          "v": 16
        },
        {
          "dir": "З",
          "deg": 270,
          "v": 13
        },
        {
          "dir": "СЗ",
          "deg": 315,
          "v": 11
        }
      ]
    },
    {
      "settlement": "Сургут",
      "stroydocsCity": "Сургут",
      "region": "Тюменская область",
      "match": "exact",
      "januaryRose": [
        {
          "dir": "С",
          "deg": 0,
          "v": 3
        },
        {
          "dir": "СВ",
          "deg": 45,
          "v": 7
        },
        {
          "dir": "В",
          "deg": 90,
          "v": 13
        },
        {
          "dir": "ЮВ",
          "deg": 135,
          "v": 10
        },
        {
          "dir": "Ю",
          "deg": 180,
          "v": 13
        },
        {
          "dir": "ЮЗ",
          "deg": 225,
          "v": 26
        },
        {
          "dir": "З",
          "deg": 270,
          "v": 22
        },
        {
          "dir": "СЗ",
          "deg": 315,
          "v": 6
        }
      ]
    },
    {
      "settlement": "Якутск",
      "stroydocsCity": "Якутск",
      "region": "Якутская АССР",
      "match": "exact",
      "januaryRose": [
        {
          "dir": "С",
          "deg": 0,
          "v": 33
        },
        {
          "dir": "СВ",
          "deg": 45,
          "v": 27
        },
        {
          "dir": "В",
          "deg": 90,
          "v": 1
        },
        {
          "dir": "ЮВ",
          "deg": 135,
          "v": 2
        },
        {
          "dir": "Ю",
          "deg": 180,
          "v": 8
        },
        {
          "dir": "ЮЗ",
          "deg": 225,
          "v": 10
        },
        {
          "dir": "З",
          "deg": 270,
          "v": 10
        },
        {
          "dir": "СЗ",
          "deg": 315,
          "v": 9
        }
      ]
    },
    {
      "settlement": "Чита",
      "stroydocsCity": "Чита",
      "region": "Читинская область",
      "match": "exact",
      "januaryRose": [
        {
          "dir": "С",
          "deg": 0,
          "v": 15
        },
        {
          "dir": "СВ",
          "deg": 45,
          "v": 3
        },
        {
          "dir": "В",
          "deg": 90,
          "v": 1
        },
        {
          "dir": "ЮВ",
          "deg": 135,
          "v": 0
        },
        {
          "dir": "Ю",
          "deg": 180,
          "v": 2
        },
        {
          "dir": "ЮЗ",
          "deg": 225,
          "v": 13
        },
        {
          "dir": "З",
          "deg": 270,
          "v": 38
        },
        {
          "dir": "СЗ",
          "deg": 315,
          "v": 28
        }
      ]
    },
    {
      "settlement": "Улан-Удэ",
      "stroydocsCity": "Улан-Удэ",
      "region": "Бурятская АССР",
      "match": "exact",
      "januaryRose": [
        {
          "dir": "С",
          "deg": 0,
          "v": 1
        },
        {
          "dir": "СВ",
          "deg": 45,
          "v": 1
        },
        {
          "dir": "В",
          "deg": 90,
          "v": 20
        },
        {
          "dir": "ЮВ",
          "deg": 135,
          "v": 6
        },
        {
          "dir": "Ю",
          "deg": 180,
          "v": 5
        },
        {
          "dir": "ЮЗ",
          "deg": 225,
          "v": 30
        },
        {
          "dir": "З",
          "deg": 270,
          "v": 31
        },
        {
          "dir": "СЗ",
          "deg": 315,
          "v": 11
        }
      ]
    },
    {
      "settlement": "Комсомольск-на-Амуре",
      "stroydocsCity": "Комсомольск-на-Амуре",
      "region": "Хаборавский край",
      "match": "exact",
      "januaryRose": [
        {
          "dir": "С",
          "deg": 0,
          "v": 26
        },
        {
          "dir": "СВ",
          "deg": 45,
          "v": 10
        },
        {
          "dir": "В",
          "deg": 90,
          "v": 1
        },
        {
          "dir": "ЮВ",
          "deg": 135,
          "v": 5
        },
        {
          "dir": "Ю",
          "deg": 180,
          "v": 53
        },
        {
          "dir": "ЮЗ",
          "deg": 225,
          "v": 4
        },
        {
          "dir": "З",
          "deg": 270,
          "v": 0
        },
        {
          "dir": "СЗ",
          "deg": 315,
          "v": 1
        }
      ]
    },
    {
      "settlement": "Благовещенск",
      "stroydocsCity": "Благовещенск",
      "region": "Амурская область",
      "match": "exact",
      "januaryRose": [
        {
          "dir": "С",
          "deg": 0,
          "v": 21
        },
        {
          "dir": "СВ",
          "deg": 45,
          "v": 5
        },
        {
          "dir": "В",
          "deg": 90,
          "v": 1
        },
        {
          "dir": "ЮВ",
          "deg": 135,
          "v": 1
        },
        {
          "dir": "Ю",
          "deg": 180,
          "v": 6
        },
        {
          "dir": "ЮЗ",
          "deg": 225,
          "v": 6
        },
        {
          "dir": "З",
          "deg": 270,
          "v": 11
        },
        {
          "dir": "СЗ",
          "deg": 315,
          "v": 49
        }
      ]
    },
    {
      "settlement": "Петропавловск-Камчатский",
      "stroydocsCity": "Петропавловск-Камчатский",
      "region": "Камчатская область",
      "match": "exact",
      "januaryRose": [
        {
          "dir": "С",
          "deg": 0,
          "v": 29
        },
        {
          "dir": "СВ",
          "deg": 45,
          "v": 6
        },
        {
          "dir": "В",
          "deg": 90,
          "v": 9
        },
        {
          "dir": "ЮВ",
          "deg": 135,
          "v": 4
        },
        {
          "dir": "Ю",
          "deg": 180,
          "v": 1
        },
        {
          "dir": "ЮЗ",
          "deg": 225,
          "v": 4
        },
        {
          "dir": "З",
          "deg": 270,
          "v": 7
        },
        {
          "dir": "СЗ",
          "deg": 315,
          "v": 44
        }
      ]
    },
    {
      "settlement": "Южно-Сахалинск",
      "stroydocsCity": "Южно-Сахалинск",
      "region": "Сахалинская область",
      "match": "exact",
      "januaryRose": [
        {
          "dir": "С",
          "deg": 0,
          "v": 74
        },
        {
          "dir": "СВ",
          "deg": 45,
          "v": 4
        },
        {
          "dir": "В",
          "deg": 90,
          "v": 1
        },
        {
          "dir": "ЮВ",
          "deg": 135,
          "v": 2
        },
        {
          "dir": "Ю",
          "deg": 180,
          "v": 4
        },
        {
          "dir": "ЮЗ",
          "deg": 225,
          "v": 2
        },
        {
          "dir": "З",
          "deg": 270,
          "v": 2
        },
        {
          "dir": "СЗ",
          "deg": 315,
          "v": 11
        }
      ]
    },
    {
      "settlement": "Сыктывкар",
      "stroydocsCity": "Сыктывкар",
      "region": "Коми АССР",
      "match": "exact",
      "januaryRose": [
        {
          "dir": "С",
          "deg": 0,
          "v": 8
        },
        {
          "dir": "СВ",
          "deg": 45,
          "v": 9
        },
        {
          "dir": "В",
          "deg": 90,
          "v": 3
        },
        {
          "dir": "ЮВ",
          "deg": 135,
          "v": 10
        },
        {
          "dir": "Ю",
          "deg": 180,
          "v": 27
        },
        {
          "dir": "ЮЗ",
          "deg": 225,
          "v": 29
        },
        {
          "dir": "З",
          "deg": 270,
          "v": 6
        },
        {
          "dir": "СЗ",
          "deg": 315,
          "v": 8
        }
      ]
    },
    {
      "settlement": "Архангельск",
      "stroydocsCity": "Архангельск",
      "region": "Архангельская область",
      "match": "exact",
      "januaryRose": [
        {
          "dir": "С",
          "deg": 0,
          "v": 7
        },
        {
          "dir": "СВ",
          "deg": 45,
          "v": 6
        },
        {
          "dir": "В",
          "deg": 90,
          "v": 13
        },
        {
          "dir": "ЮВ",
          "deg": 135,
          "v": 19
        },
        {
          "dir": "Ю",
          "deg": 180,
          "v": 15
        },
        {
          "dir": "ЮЗ",
          "deg": 225,
          "v": 20
        },
        {
          "dir": "З",
          "deg": 270,
          "v": 12
        },
        {
          "dir": "СЗ",
          "deg": 315,
          "v": 8
        }
      ]
    },
    {
      "settlement": "Вологда",
      "stroydocsCity": "Вологда",
      "region": "Вологодская область",
      "match": "exact",
      "januaryRose": [
        {
          "dir": "С",
          "deg": 0,
          "v": 12
        },
        {
          "dir": "СВ",
          "deg": 45,
          "v": 5
        },
        {
          "dir": "В",
          "deg": 90,
          "v": 4
        },
        {
          "dir": "ЮВ",
          "deg": 135,
          "v": 16
        },
        {
          "dir": "Ю",
          "deg": 180,
          "v": 16
        },
        {
          "dir": "ЮЗ",
          "deg": 225,
          "v": 20
        },
        {
          "dir": "З",
          "deg": 270,
          "v": 13
        },
        {
          "dir": "СЗ",
          "deg": 315,
          "v": 14
        }
      ]
    },
    {
      "settlement": "Псков",
      "stroydocsCity": "Псков",
      "region": "Псковская область",
      "match": "exact",
      "januaryRose": [
        {
          "dir": "С",
          "deg": 0,
          "v": 6
        },
        {
          "dir": "СВ",
          "deg": 45,
          "v": 7
        },
        {
          "dir": "В",
          "deg": 90,
          "v": 10
        },
        {
          "dir": "ЮВ",
          "deg": 135,
          "v": 15
        },
        {
          "dir": "Ю",
          "deg": 180,
          "v": 22
        },
        {
          "dir": "ЮЗ",
          "deg": 225,
          "v": 16
        },
        {
          "dir": "З",
          "deg": 270,
          "v": 11
        },
        {
          "dir": "СЗ",
          "deg": 315,
          "v": 13
        }
      ]
    },
    {
      "settlement": "Великий Новгород",
      "stroydocsCity": "Новгород",
      "region": "Новгородская область",
      "match": "exact",
      "januaryRose": [
        {
          "dir": "С",
          "deg": 0,
          "v": 10
        },
        {
          "dir": "СВ",
          "deg": 45,
          "v": 10
        },
        {
          "dir": "В",
          "deg": 90,
          "v": 6
        },
        {
          "dir": "ЮВ",
          "deg": 135,
          "v": 14
        },
        {
          "dir": "Ю",
          "deg": 180,
          "v": 22
        },
        {
          "dir": "ЮЗ",
          "deg": 225,
          "v": 19
        },
        {
          "dir": "З",
          "deg": 270,
          "v": 10
        },
        {
          "dir": "СЗ",
          "deg": 315,
          "v": 9
        }
      ]
    },
    {
      "settlement": "Орск",
      "stroydocsCity": "Орск",
      "region": "Оренбургская область",
      "match": "exact",
      "januaryRose": [
        {
          "dir": "С",
          "deg": 0,
          "v": 13
        },
        {
          "dir": "СВ",
          "deg": 45,
          "v": 20
        },
        {
          "dir": "В",
          "deg": 90,
          "v": 10
        },
        {
          "dir": "ЮВ",
          "deg": 135,
          "v": 10
        },
        {
          "dir": "Ю",
          "deg": 180,
          "v": 5
        },
        {
          "dir": "ЮЗ",
          "deg": 225,
          "v": 16
        },
        {
          "dir": "З",
          "deg": 270,
          "v": 24
        },
        {
          "dir": "СЗ",
          "deg": 315,
          "v": 2
        }
      ]
    },
    {
      "settlement": "Нижний Тагил",
      "stroydocsCity": "Нижний Тагил",
      "region": "Свердловская область",
      "match": "exact",
      "januaryRose": [
        {
          "dir": "С",
          "deg": 0,
          "v": 6
        },
        {
          "dir": "СВ",
          "deg": 45,
          "v": 4
        },
        {
          "dir": "В",
          "deg": 90,
          "v": 3
        },
        {
          "dir": "ЮВ",
          "deg": 135,
          "v": 12
        },
        {
          "dir": "Ю",
          "deg": 180,
          "v": 12
        },
        {
          "dir": "ЮЗ",
          "deg": 225,
          "v": 38
        },
        {
          "dir": "З",
          "deg": 270,
          "v": 22
        },
        {
          "dir": "СЗ",
          "deg": 315,
          "v": 3
        }
      ]
    },
    {
      "settlement": "Анадырь",
      "stroydocsCity": "Анадырь",
      "region": "Магаданская область",
      "match": "exact",
      "januaryRose": [
        {
          "dir": "С",
          "deg": 0,
          "v": 11
        },
        {
          "dir": "СВ",
          "deg": 45,
          "v": 16
        },
        {
          "dir": "В",
          "deg": 90,
          "v": 10
        },
        {
          "dir": "ЮВ",
          "deg": 135,
          "v": 9
        },
        {
          "dir": "Ю",
          "deg": 180,
          "v": 2
        },
        {
          "dir": "ЮЗ",
          "deg": 225,
          "v": 1
        },
        {
          "dir": "З",
          "deg": 270,
          "v": 10
        },
        {
          "dir": "СЗ",
          "deg": 315,
          "v": 41
        }
      ]
    },
    {
      "settlement": "Магадан",
      "stroydocsCity": "Нагаева, бухта",
      "region": "Магаданская область",
      "match": "exact",
      "januaryRose": [
        {
          "dir": "С",
          "deg": 0,
          "v": 1
        },
        {
          "dir": "СВ",
          "deg": 45,
          "v": 63
        },
        {
          "dir": "В",
          "deg": 90,
          "v": 32
        },
        {
          "dir": "ЮВ",
          "deg": 135,
          "v": 1
        },
        {
          "dir": "Ю",
          "deg": 180,
          "v": 0
        },
        {
          "dir": "ЮЗ",
          "deg": 225,
          "v": 1
        },
        {
          "dir": "З",
          "deg": 270,
          "v": 2
        },
        {
          "dir": "СЗ",
          "deg": 315,
          "v": 0
        }
      ]
    },
    {
      "settlement": "Элиста",
      "stroydocsCity": "Элиста",
      "region": "Калмыцкая АССР",
      "match": "exact",
      "januaryRose": [
        {
          "dir": "С",
          "deg": 0,
          "v": 7
        },
        {
          "dir": "СВ",
          "deg": 45,
          "v": 17
        },
        {
          "dir": "В",
          "deg": 90,
          "v": 21
        },
        {
          "dir": "ЮВ",
          "deg": 135,
          "v": 11
        },
        {
          "dir": "Ю",
          "deg": 180,
          "v": 8
        },
        {
          "dir": "ЮЗ",
          "deg": 225,
          "v": 8
        },
        {
          "dir": "З",
          "deg": 270,
          "v": 20
        },
        {
          "dir": "СЗ",
          "deg": 315,
          "v": 8
        }
      ]
    },
    {
      "settlement": "Абакан",
      "stroydocsCity": "Абакан",
      "region": "Красноярский край",
      "match": "exact",
      "januaryRose": [
        {
          "dir": "С",
          "deg": 0,
          "v": 19
        },
        {
          "dir": "СВ",
          "deg": 45,
          "v": 1
        },
        {
          "dir": "В",
          "deg": 90,
          "v": 1
        },
        {
          "dir": "ЮВ",
          "deg": 135,
          "v": 7
        },
        {
          "dir": "Ю",
          "deg": 180,
          "v": 15
        },
        {
          "dir": "ЮЗ",
          "deg": 225,
          "v": 36
        },
        {
          "dir": "З",
          "deg": 270,
          "v": 11
        },
        {
          "dir": "СЗ",
          "deg": 315,
          "v": 10
        }
      ]
    },
    {
      "settlement": "Горно-Алтайск",
      "stroydocsCity": "Горно-Алтайск",
      "region": "Алтайский край",
      "match": "exact",
      "januaryRose": [
        {
          "dir": "С",
          "deg": 0,
          "v": 9
        },
        {
          "dir": "СВ",
          "deg": 45,
          "v": 1
        },
        {
          "dir": "В",
          "deg": 90,
          "v": 4
        },
        {
          "dir": "ЮВ",
          "deg": 135,
          "v": 24
        },
        {
          "dir": "Ю",
          "deg": 180,
          "v": 43
        },
        {
          "dir": "ЮЗ",
          "deg": 225,
          "v": 4
        },
        {
          "dir": "З",
          "deg": 270,
          "v": 2
        },
        {
          "dir": "СЗ",
          "deg": 315,
          "v": 13
        }
      ]
    },
    {
      "settlement": "Кызыл",
      "stroydocsCity": "Кызыл",
      "region": "Тувинская АГСР",
      "match": "exact",
      "januaryRose": [
        {
          "dir": "С",
          "deg": 0,
          "v": 5
        },
        {
          "dir": "СВ",
          "deg": 45,
          "v": 13
        },
        {
          "dir": "В",
          "deg": 90,
          "v": 44
        },
        {
          "dir": "ЮВ",
          "deg": 135,
          "v": 15
        },
        {
          "dir": "Ю",
          "deg": 180,
          "v": 6
        },
        {
          "dir": "ЮЗ",
          "deg": 225,
          "v": 10
        },
        {
          "dir": "З",
          "deg": 270,
          "v": 3
        },
        {
          "dir": "СЗ",
          "deg": 315,
          "v": 4
        }
      ]
    },
    {
      "settlement": "Нальчик",
      "stroydocsCity": "Нальчик",
      "region": "Кабардино-Балкарская АССР",
      "match": "exact",
      "januaryRose": [
        {
          "dir": "С",
          "deg": 0,
          "v": 7
        },
        {
          "dir": "СВ",
          "deg": 45,
          "v": 18
        },
        {
          "dir": "В",
          "deg": 90,
          "v": 16
        },
        {
          "dir": "ЮВ",
          "deg": 135,
          "v": 7
        },
        {
          "dir": "Ю",
          "deg": 180,
          "v": 5
        },
        {
          "dir": "ЮЗ",
          "deg": 225,
          "v": 34
        },
        {
          "dir": "З",
          "deg": 270,
          "v": 7
        },
        {
          "dir": "СЗ",
          "deg": 315,
          "v": 6
        }
      ]
    },
    {
      "settlement": "Майкоп",
      "stroydocsCity": "Майкоп",
      "region": "Краснодарский край",
      "match": "exact",
      "januaryRose": [
        {
          "dir": "С",
          "deg": 0,
          "v": 8
        },
        {
          "dir": "СВ",
          "deg": 45,
          "v": 10
        },
        {
          "dir": "В",
          "deg": 90,
          "v": 10
        },
        {
          "dir": "ЮВ",
          "deg": 135,
          "v": 8
        },
        {
          "dir": "Ю",
          "deg": 180,
          "v": 27
        },
        {
          "dir": "ЮЗ",
          "deg": 225,
          "v": 13
        },
        {
          "dir": "З",
          "deg": 270,
          "v": 10
        },
        {
          "dir": "СЗ",
          "deg": 315,
          "v": 14
        }
      ]
    },
    {
      "settlement": "Симферополь",
      "stroydocsCity": "Симферополь",
      "region": "Крымская область",
      "match": "exact",
      "januaryRose": [
        {
          "dir": "С",
          "deg": 0,
          "v": 5
        },
        {
          "dir": "СВ",
          "deg": 45,
          "v": 23
        },
        {
          "dir": "В",
          "deg": 90,
          "v": 11
        },
        {
          "dir": "ЮВ",
          "deg": 135,
          "v": 17
        },
        {
          "dir": "Ю",
          "deg": 180,
          "v": 12
        },
        {
          "dir": "ЮЗ",
          "deg": 225,
          "v": 19
        },
        {
          "dir": "З",
          "deg": 270,
          "v": 7
        },
        {
          "dir": "СЗ",
          "deg": 315,
          "v": 6
        }
      ]
    },
    {
      "settlement": "Севастополь",
      "stroydocsCity": "Севастополь",
      "region": "Крымская область",
      "match": "exact",
      "januaryRose": [
        {
          "dir": "С",
          "deg": 0,
          "v": 13
        },
        {
          "dir": "СВ",
          "deg": 45,
          "v": 30
        },
        {
          "dir": "В",
          "deg": 90,
          "v": 10
        },
        {
          "dir": "ЮВ",
          "deg": 135,
          "v": 8
        },
        {
          "dir": "Ю",
          "deg": 180,
          "v": 22
        },
        {
          "dir": "ЮЗ",
          "deg": 225,
          "v": 7
        },
        {
          "dir": "З",
          "deg": 270,
          "v": 5
        },
        {
          "dir": "СЗ",
          "deg": 315,
          "v": 5
        }
      ]
    },
    {
      "settlement": "Каменск-Шахтинск",
      "stroydocsCity": "Каменск-Шахтинский",
      "region": "Ростовская область",
      "match": "exact",
      "januaryRose": [
        {
          "dir": "С",
          "deg": 0,
          "v": 5
        },
        {
          "dir": "СВ",
          "deg": 45,
          "v": 10
        },
        {
          "dir": "В",
          "deg": 90,
          "v": 28
        },
        {
          "dir": "ЮВ",
          "deg": 135,
          "v": 13
        },
        {
          "dir": "Ю",
          "deg": 180,
          "v": 5
        },
        {
          "dir": "ЮЗ",
          "deg": 225,
          "v": 16
        },
        {
          "dir": "З",
          "deg": 270,
          "v": 15
        },
        {
          "dir": "СЗ",
          "deg": 315,
          "v": 8
        }
      ]
    },
    {
      "settlement": "Новороссийск",
      "stroydocsCity": "Новороссийск",
      "region": "Краснодарский край",
      "match": "exact",
      "januaryRose": [
        {
          "dir": "С",
          "deg": 0,
          "v": 16
        },
        {
          "dir": "СВ",
          "deg": 45,
          "v": 11
        },
        {
          "dir": "В",
          "deg": 90,
          "v": 1
        },
        {
          "dir": "ЮВ",
          "deg": 135,
          "v": 11
        },
        {
          "dir": "Ю",
          "deg": 180,
          "v": 16
        },
        {
          "dir": "ЮЗ",
          "deg": 225,
          "v": 6
        },
        {
          "dir": "З",
          "deg": 270,
          "v": 4
        },
        {
          "dir": "СЗ",
          "deg": 315,
          "v": 35
        }
      ]
    },
    {
      "settlement": "Бийск",
      "stroydocsCity": "Бийск",
      "region": "Алтайский край",
      "match": "exact",
      "januaryRose": [
        {
          "dir": "С",
          "deg": 0,
          "v": 3
        },
        {
          "dir": "СВ",
          "deg": 45,
          "v": 23
        },
        {
          "dir": "В",
          "deg": 90,
          "v": 23
        },
        {
          "dir": "ЮВ",
          "deg": 135,
          "v": 10
        },
        {
          "dir": "Ю",
          "deg": 180,
          "v": 7
        },
        {
          "dir": "ЮЗ",
          "deg": 225,
          "v": 19
        },
        {
          "dir": "З",
          "deg": 270,
          "v": 12
        },
        {
          "dir": "СЗ",
          "deg": 315,
          "v": 3
        }
      ]
    },
    {
      "settlement": "Армавир",
      "stroydocsCity": "Армавир",
      "region": "Краснодарский край",
      "match": "exact",
      "januaryRose": [
        {
          "dir": "С",
          "deg": 0,
          "v": 2
        },
        {
          "dir": "СВ",
          "deg": 45,
          "v": 4
        },
        {
          "dir": "В",
          "deg": 90,
          "v": 9
        },
        {
          "dir": "ЮВ",
          "deg": 135,
          "v": 59
        },
        {
          "dir": "Ю",
          "deg": 180,
          "v": 3
        },
        {
          "dir": "ЮЗ",
          "deg": 225,
          "v": 7
        },
        {
          "dir": "З",
          "deg": 270,
          "v": 12
        },
        {
          "dir": "СЗ",
          "deg": 315,
          "v": 4
        }
      ]
    },
    {
      "settlement": "Уссурийск",
      "stroydocsCity": "Уссурийск",
      "region": "Приморский край",
      "match": "exact",
      "januaryRose": [
        {
          "dir": "С",
          "deg": 0,
          "v": 35
        },
        {
          "dir": "СВ",
          "deg": 45,
          "v": 10
        },
        {
          "dir": "В",
          "deg": 90,
          "v": 5
        },
        {
          "dir": "ЮВ",
          "deg": 135,
          "v": 17
        },
        {
          "dir": "Ю",
          "deg": 180,
          "v": 8
        },
        {
          "dir": "ЮЗ",
          "deg": 225,
          "v": 1
        },
        {
          "dir": "З",
          "deg": 270,
          "v": 2
        },
        {
          "dir": "СЗ",
          "deg": 315,
          "v": 22
        }
      ]
    },
    {
      "settlement": "Находка",
      "stroydocsCity": "Находка, бухта",
      "region": "Приморский край",
      "match": "exact",
      "januaryRose": [
        {
          "dir": "С",
          "deg": 0,
          "v": 31
        },
        {
          "dir": "СВ",
          "deg": 45,
          "v": 38
        },
        {
          "dir": "В",
          "deg": 90,
          "v": 1
        },
        {
          "dir": "ЮВ",
          "deg": 135,
          "v": 1
        },
        {
          "dir": "Ю",
          "deg": 180,
          "v": 0
        },
        {
          "dir": "ЮЗ",
          "deg": 225,
          "v": 0
        },
        {
          "dir": "З",
          "deg": 270,
          "v": 10
        },
        {
          "dir": "СЗ",
          "deg": 315,
          "v": 19
        }
      ]
    },
    {
      "settlement": "Салехард",
      "stroydocsCity": "Салехард",
      "region": "Тюменская область",
      "match": "exact",
      "januaryRose": [
        {
          "dir": "С",
          "deg": 0,
          "v": 3
        },
        {
          "dir": "СВ",
          "deg": 45,
          "v": 11
        },
        {
          "dir": "В",
          "deg": 90,
          "v": 3
        },
        {
          "dir": "ЮВ",
          "deg": 135,
          "v": 14
        },
        {
          "dir": "Ю",
          "deg": 180,
          "v": 23
        },
        {
          "dir": "ЮЗ",
          "deg": 225,
          "v": 23
        },
        {
          "dir": "З",
          "deg": 270,
          "v": 6
        },
        {
          "dir": "СЗ",
          "deg": 315,
          "v": 9
        }
      ]
    },
    {
      "settlement": "Камышин",
      "stroydocsCity": "Камышин",
      "region": "Волгоградская область",
      "match": "exact",
      "januaryRose": [
        {
          "dir": "С",
          "deg": 0,
          "v": 4
        },
        {
          "dir": "СВ",
          "deg": 45,
          "v": 15
        },
        {
          "dir": "В",
          "deg": 90,
          "v": 10
        },
        {
          "dir": "ЮВ",
          "deg": 135,
          "v": 9
        },
        {
          "dir": "Ю",
          "deg": 180,
          "v": 13
        },
        {
          "dir": "ЮЗ",
          "deg": 225,
          "v": 9
        },
        {
          "dir": "З",
          "deg": 270,
          "v": 19
        },
        {
          "dir": "СЗ",
          "deg": 315,
          "v": 21
        }
      ]
    }
  ]
}